dynaconf/VERSION
dynaconf/__init__.py
dynaconf/base.py
dynaconf/cli.py
dynaconf/constants.py
dynaconf/default_settings.py
dynaconf/hooking.py
dynaconf/test_settings.py
dynaconf/validator.py
dynaconf/validator_conditions.py
dynaconf/contrib/__init__.py
dynaconf/contrib/django_dynaconf_v2.py
dynaconf/contrib/flask_dynaconf.py
dynaconf/loaders/__init__.py
dynaconf/loaders/base.py
dynaconf/loaders/env_loader.py
dynaconf/loaders/ini_loader.py
dynaconf/loaders/json_loader.py
dynaconf/loaders/py_loader.py
dynaconf/loaders/redis_loader.py
dynaconf/loaders/toml_loader.py
dynaconf/loaders/vault_loader.py
dynaconf/loaders/yaml_loader.py
dynaconf/strategies/__init__.py
dynaconf/strategies/filtering.py
dynaconf/utils/__init__.py
dynaconf/utils/boxing.py
dynaconf/utils/files.py
dynaconf/utils/functional.py
dynaconf/utils/inspect.py
dynaconf/utils/parse_conf.py
dynaconf/vendor/__init__.py
dynaconf/vendor/box/__init__.py
dynaconf/vendor/box/box.py
dynaconf/vendor/box/box_list.py
dynaconf/vendor/box/config_box.py
dynaconf/vendor/box/converters.py
dynaconf/vendor/box/exceptions.py
dynaconf/vendor/box/from_file.py
dynaconf/vendor/box/shorthand_box.py
dynaconf/vendor/click/__init__.py
dynaconf/vendor/click/_bashcomplete.py
dynaconf/vendor/click/_compat.py
dynaconf/vendor/click/_termui_impl.py
dynaconf/vendor/click/_textwrap.py
dynaconf/vendor/click/_unicodefun.py
dynaconf/vendor/click/_winconsole.py
dynaconf/vendor/click/core.py
dynaconf/vendor/click/decorators.py
dynaconf/vendor/click/exceptions.py
dynaconf/vendor/click/formatting.py
dynaconf/vendor/click/globals.py
dynaconf/vendor/click/parser.py
dynaconf/vendor/click/termui.py
dynaconf/vendor/click/testing.py
dynaconf/vendor/click/types.py
dynaconf/vendor/click/utils.py
dynaconf/vendor/dotenv/__init__.py
dynaconf/vendor/dotenv/cli.py
dynaconf/vendor/dotenv/compat.py
dynaconf/vendor/dotenv/ipython.py
dynaconf/vendor/dotenv/main.py
dynaconf/vendor/dotenv/parser.py
dynaconf/vendor/dotenv/version.py
dynaconf/vendor/ruamel/__init__.py
dynaconf-3.2.7.dist-info/LICENSE
dynaconf-3.2.7.dist-info/METADATA
dynaconf-3.2.7.dist-info/WHEEL
dynaconf-3.2.7.dist-info/box-LICENSE.txt
dynaconf-3.2.7.dist-info/click-LICENSE.rst
dynaconf-3.2.7.dist-info/entry_points.txt
dynaconf-3.2.7.dist-info/licenses.sh
dynaconf-3.2.7.dist-info/python-dotenv-LICENSE.txt
dynaconf-3.2.7.dist-info/ruamel.yaml-LICENSE.txt
dynaconf-3.2.7.dist-info/toml-LICENSE.txt
dynaconf-3.2.7.dist-info/tomli-LICENSE.txt
dynaconf-3.2.7.dist-info/top_level.txt
dynaconf-3.2.7.dist-info/vendor_versions.txt
dynaconf-3.2.7.dist-info/RECORD
