Metadata-Version: 2.1
Name: dynaconf
Version: 3.2.7
Summary: The dynamic configurator for your Python Project
Home-page: https://github.com/dynaconf/dynaconf
Author: Bruno Rocha
Author-email: rochacbruno@gmail.com
License: MIT
Platform: any
Classifier: Development Status :: 5 - Production/Stable
Classifier: Framework :: Django
Classifier: Framework :: Flask
Classifier: Intended Audience :: Developers
Classifier: License :: OSI Approved :: MIT License
Classifier: Natural Language :: English
Classifier: Operating System :: OS Independent
Classifier: Programming Language :: Python
Classifier: Programming Language :: Python :: 3
Classifier: Programming Language :: Python :: 3 :: Only
Classifier: Programming Language :: Python :: 3.8
Classifier: Programming Language :: Python :: 3.9
Classifier: Programming Language :: Python :: 3.10
Classifier: Programming Language :: Python :: 3.11
Classifier: Topic :: Utilities
Classifier: Topic :: Software Development :: Libraries
Classifier: Topic :: Software Development :: Libraries :: Python Modules
Requires-Python: >=3.8
Provides-Extra: redis
Provides-Extra: vault
Provides-Extra: yaml
Provides-Extra: toml
Provides-Extra: ini
Provides-Extra: configobj
Provides-Extra: all
Provides-Extra: test
License-File: LICENSE
License-File: vendor_licenses/box-LICENSE.txt
License-File: vendor_licenses/click-LICENSE.rst
License-File: vendor_licenses/licenses.sh
License-File: vendor_licenses/python-dotenv-LICENSE.txt
License-File: vendor_licenses/ruamel.yaml-LICENSE.txt
License-File: vendor_licenses/toml-LICENSE.txt
License-File: vendor_licenses/tomli-LICENSE.txt
License-File: vendor_licenses/vendor_versions.txt
